dmongo/__init__.py
dmongo/dmongo.py
dmongo-0.1.0.dist-info/METADATA
dmongo-0.1.0.dist-info/WHEEL
dmongo-0.1.0.dist-info/top_level.txt
dmongo-0.1.0.dist-info/RECORD
