Metadata-Version: 2.1
Name: dmongo
Version: 0.1.0
Summary: A python library for communicating and Querying mongodb
Home-page: UNKNOWN
Author: Geoffrey Israel
Author-email: israelgeoffrey13@gmail.com
License: MIT
Platform: UNKNOWN
Requires-Dist: pymongo (==3.12.1)
